[
  {
    "name": "login",
    "path": "/login",
    "component": "C:\\\\Users\\\\Admin\\\\Documents\\\\web\\\\AmanZ\\\\pages\\\\login.vue",
    "chunkName": "pages/login"
  },
  {
    "name": "products",
    "path": "/products",
    "component": "C:\\\\Users\\\\Admin\\\\Documents\\\\web\\\\AmanZ\\\\pages\\\\products.vue",
    "chunkName": "pages/products"
  },
  {
    "name": "registrate",
    "path": "/registrate",
    "component": "C:\\\\Users\\\\Admin\\\\Documents\\\\web\\\\AmanZ\\\\pages\\\\registrate.vue",
    "chunkName": "pages/registrate"
  },
  {
    "name": "reset",
    "path": "/reset",
    "component": "C:\\\\Users\\\\Admin\\\\Documents\\\\web\\\\AmanZ\\\\pages\\\\reset.vue",
    "chunkName": "pages/reset"
  },
  {
    "name": "resetpassword",
    "path": "/resetpassword",
    "component": "C:\\\\Users\\\\Admin\\\\Documents\\\\web\\\\AmanZ\\\\pages\\\\resetpassword.vue",
    "chunkName": "pages/resetpassword"
  },
  {
    "name": "verification",
    "path": "/verification",
    "component": "C:\\\\Users\\\\Admin\\\\Documents\\\\web\\\\AmanZ\\\\pages\\\\verification.vue",
    "chunkName": "pages/verification"
  },
  {
    "name": "index",
    "path": "/",
    "component": "C:\\\\Users\\\\Admin\\\\Documents\\\\web\\\\AmanZ\\\\pages\\\\index.vue",
    "chunkName": "pages/index"
  }
]
